Metadata-Version: 1.0
Name: distributions-udacity-course
Version: 0.1
Summary: Gaussian and Binomial distributions
Home-page: UNKNOWN
Author: Ardacandra Subiantoro
Author-email: ardacandrasubiantoro@gmail.com
License: UNKNOWN
Platform: UNKNOWN
